qualys_tbx/README.md
qualys_tbx/__init__.py
qualys_tbx/qualystbx.py
qualys_tbx/qualystbx_withvenv.py
qualys_tbx/qtbx_lib/__init__.py
qualys_tbx/qtbx_lib/qtbx_lib_argparser.py
qualys_tbx/qtbx_lib/qtbx_lib_authentication.py
qualys_tbx/qtbx_lib/qtbx_lib_config.py
qualys_tbx/qtbx_lib/qtbx_lib_functions.py
qualys_tbx/qtbx_lib/qtbx_lib_logger.py
qualys_tbx/qtbx_policy_merge/__init__.py
qualys_tbx/qtbx_policy_merge/policy_merge_01.py
qualystbx-0.47.0.dist-info/LICENSE.txt
qualystbx-0.47.0.dist-info/METADATA
qualystbx-0.47.0.dist-info/WHEEL
qualystbx-0.47.0.dist-info/entry_points.txt
qualystbx-0.47.0.dist-info/top_level.txt
qualystbx-0.47.0.dist-info/RECORD
