Metadata-Version: 2.1
Name: qualystbx
Version: 0.47.0
Summary: Qualys Tool Box - Tools for running various functions in Qualys.
Home-page: https://pypi.org/project/qualystbx/
Author: David Gregory
Author-email: dgregory@qualys.com, dave@davidgregory.com
License: Apache
Project-URL: Documentation, https://dg-cafe.github.io/qualystbx/
Keywords: qualys,qualystoolbox,qualys.com,david gregory,qualystbx,qualysapi
Classifier: Development Status :: 4 - Beta
Classifier: Intended Audience :: Developers
Classifier: License :: OSI Approved :: Apache Software License
Classifier: Programming Language :: Python :: 3.9
Classifier: Programming Language :: Python :: 3.10
Classifier: Programming Language :: Python :: 3.11
Classifier: Programming Language :: Python :: 3 :: Only
Requires-Python: >=3.9.0
License-File: LICENSE.txt
